LAB-0/eg2.v
module eg2(x1, x2, x3, x4, f, g, h);
input x1, x2, x3, x4;
output f, g, h;

wire and1, and2, or1;
wire not1, not2;
wire or2, or3, and3;

// g = x1·x3 + x2·x4
and a1(and1, x1, x3);
and a2(and2, x2, x4);
or o1(g, and1, and2);

// h = (x1 + ~x3)·(~x2 + x4)
not n1(not1, x3);
not n2(not2, x2);
or o2(or2, x1, not1);
or o3(or3, not2, x4);
and a3(h, or2, or3);

// f = g + h
or o4(f, g, h);

endmodule

LAB-0/eg2_tb.v
`timescale 1ns/1ns
`include "eg2.v"

module eg2_tb();
reg x1, x2, x3, x4;
wire f, g, h;

eg2 eg(x1, x2, x3, x4, f, g, h);

initial begin
  $dumpfile("eg2.vcd");
  $dumpvars(0, eg2_tb);

  x1=1'b0; x2=1'b0; x3=1'b0; x4=1'b0; #20;
  x1=1'b0; x2=1'b0; x3=1'b0; x4=1'b1; #20;
  x1=1'b0; x2=1'b0; x3=1'b1; x4=1'b0; #20;
  x1=1'b0; x2=1'b0; x3=1'b1; x4=1'b1; #20;

  x1=1'b0; x2=1'b1; x3=1'b0; x4=1'b0; #20;
  x1=1'b0; x2=1'b1; x3=1'b0; x4=1'b1; #20;
  x1=1'b0; x2=1'b1; x3=1'b1; x4=1'b0; #20;
  x1=1'b0; x2=1'b1; x3=1'b1; x4=1'b1; #20;

  x1=1'b1; x2=1'b0; x3=1'b0; x4=1'b0; #20;
  x1=1'b1; x2=1'b0; x3=1'b0; x4=1'b1; #20;
  x1=1'b1; x2=1'b0; x3=1'b1; x4=1'b0; #20;
  x1=1'b1; x2=1'b0; x3=1'b1; x4=1'b1; #20;

  x1=1'b1; x2=1'b1; x3=1'b0; x4=1'b0; #20;
  x1=1'b1; x2=1'b1; x3=1'b0; x4=1'b1; #20;
  x1=1'b1; x2=1'b1; x3=1'b1; x4=1'b0; #20;
  x1=1'b1; x2=1'b1; x3=1'b1; x4=1'b1; #20;

  $display("Test complete");
end

endmodule

LAB-0/eg2.vcd
$date
	Thu Jul 31 20:59:16 2025
$end
$version
	Icarus Verilog
$end
$timescale
	1ns
$end
$scope module eg2_tb $end
$var wire 1 ! h $end
$var wire 1 " g $end
$var wire 1 # f $end
$var reg 1 $ x1 $end
$var reg 1 % x2 $end
$var reg 1 & x3 $end
$var reg 1 ' x4 $end
$scope module eg $end
$var wire 1 ( and1 $end
$var wire 1 ) and2 $end
$var wire 1 # f $end
$var wire 1 " g $end
$var wire 1 ! h $end
$var wire 1 * not1 $end
$var wire 1 + not2 $end
$var wire 1 , or2 $end
$var wire 1 - or3 $end
$var wire 1 $ x1 $end
$var wire 1 % x2 $end
$var wire 1 & x3 $end
$var wire 1 ' x4 $end
$upscope $end
$upscope $end
$enddefinitions $end
$comment Show the parameter values. $end
$dumpall
$end
#0
$dumpvars
1-
1,
1+
1*
0)
0(
0'
0&
0%
0$
1#
0"
1!
$end
#20
1'
#40
0#
0!
0,
0*
0'
1&
#60
1'
#80
1,
0-
1*
0+
0'
0&
1%
#100
1#
1"
1!
1)
1-
1'
#120
0#
0"
0!
0,
0)
0-
0*
0'
1&
#140
1#
1"
1)
1-
1'
#160
0"
1!
1*
0)
1+
1,
0'
0&
0%
1$
#180
1'
#200
1"
1(
0*
0'
1&
#220
1'
#240
0#
0!
0"
0-
0(
1*
0+
0'
0&
1%
#260
1#
1"
1!
1)
1-
1'
#280
0!
0)
0-
1(
0*
0'
1&
#300
1!
1)
1-
1'
